swimlane/__init__.py
swimlane/exceptions.py
swimlane/core/__init__.py
swimlane/core/bulk.py
swimlane/core/cache.py
swimlane/core/client.py
swimlane/core/cursor.py
swimlane/core/resolver.py
swimlane/core/search.py
swimlane/core/wrappedsession.py
swimlane/core/adapters/__init__.py
swimlane/core/adapters/app.py
swimlane/core/adapters/app_revision.py
swimlane/core/adapters/helper.py
swimlane/core/adapters/record.py
swimlane/core/adapters/record_revision.py
swimlane/core/adapters/report.py
swimlane/core/adapters/task.py
swimlane/core/adapters/usergroup.py
swimlane/core/fields/__init__.py
swimlane/core/fields/attachment.py
swimlane/core/fields/comment.py
swimlane/core/fields/datetime.py
swimlane/core/fields/history.py
swimlane/core/fields/list.py
swimlane/core/fields/number.py
swimlane/core/fields/reference.py
swimlane/core/fields/text.py
swimlane/core/fields/tracking.py
swimlane/core/fields/usergroup.py
swimlane/core/fields/valueslist.py
swimlane/core/fields/base/__init__.py
swimlane/core/fields/base/cursor.py
swimlane/core/fields/base/field.py
swimlane/core/fields/base/multiselect.py
swimlane/core/resources/__init__.py
swimlane/core/resources/app.py
swimlane/core/resources/app_revision.py
swimlane/core/resources/attachment.py
swimlane/core/resources/base.py
swimlane/core/resources/comment.py
swimlane/core/resources/record.py
swimlane/core/resources/record_revision.py
swimlane/core/resources/report.py
swimlane/core/resources/revision_base.py
swimlane/core/resources/task.py
swimlane/core/resources/usergroup.py
swimlane/utils/__init__.py
swimlane/utils/date_validator.py
swimlane/utils/list_validator.py
swimlane/utils/str_validator.py
swimlane/utils/version.py
swimlane-10.19.0.dist-info/licenses/LICENSE
swimlane-10.19.0.dist-info/METADATA
swimlane-10.19.0.dist-info/WHEEL
swimlane-10.19.0.dist-info/top_level.txt
swimlane-10.19.0.dist-info/RECORD
