Metadata-Version: 2.4
Name: swimlane
Version: 10.19.0
Summary: Python driver for the Swimlane API
Home-page: https://github.com/swimlane/swimlane-python
Author: Swimlane
Author-email: info@swimlane.com
License: AGPLv3
Classifier: License :: OSI Approved :: GNU Affero General Public License v3
Classifier: Development Status :: 5 - Production/Stable
Classifier: Programming Language :: Python
Classifier: Programming Language :: Python :: 3.6
Classifier: Programming Language :: Python :: 3.7
Classifier: Programming Language :: Python :: 3.8
Classifier: Programming Language :: Python :: 3.9
Classifier: Programming Language :: Python :: 3.10
Classifier: Programming Language :: Python :: 3.11
Classifier: Programming Language :: Python :: 3.12
Requires-Python: >=3.6
License-File: LICENSE
Requires-Dist: cachetools>=4.2.4
Requires-Dist: certifi==2024.7.4
Requires-Dist: pendulum==2.1.2; python_version <= "3.7"
Requires-Dist: pendulum==3.0.0; python_version >= "3.8"
Requires-Dist: pyjwt>=2.4.0
Requires-Dist: pyuri<0.4,>=0.3
Requires-Dist: requests[security]<3,>=2
Requires-Dist: six>=1.12.0
Requires-Dist: sortedcontainers==2.4.0
Requires-Dist: shortid==0.1.2
Dynamic: author
Dynamic: author-email
Dynamic: classifier
Dynamic: description
Dynamic: description-content-type
Dynamic: home-page
Dynamic: license
Dynamic: license-file
Dynamic: requires-dist
Dynamic: requires-python
Dynamic: summary
